spaTrack/__init__.py
spaTrack/more_time/__init__.py
spaTrack/more_time/animate_transfer.py
spaTrack/more_time/transfer_matrix.py
spaTrack/more_time/utils.py
spaTrack/more_time/visual.py
spaTrack/single_time/Pgene.py
spaTrack/single_time/__init__.py
spaTrack/single_time/analysis.py
spaTrack/single_time/gene_regulation.py
spaTrack/single_time/lap.py
spaTrack/single_time/utils.py
spaTrack/single_time/vectorfield.py
spaTrack/single_time/velocity.py
spaTrack-0.0.1.dist-info/METADATA
spaTrack-0.0.1.dist-info/WHEEL
spaTrack-0.0.1.dist-info/top_level.txt
spaTrack-0.0.1.dist-info/RECORD
