Metadata-Version: 2.1
Name: spaTrack
Version: 0.0.1
Summary: an algorithm that combine both gene expression and spot location to inference cell trajectory
Home-page: https://github.com/yzf072/spaTrack
Author: yzf072
Author-email: yzfff6@outlook.com
Classifier: Programming Language :: Python :: 3
Classifier: Programming Language :: Python :: 3.9
Requires-Python: >=3.7
Requires-Dist: pot >=0.9.0
Requires-Dist: scanpy >=1.9.3
Requires-Dist: plotly >=5.15.0
Requires-Dist: ipywidgets >=8.0.7
Requires-Dist: pygam >=0.8.0
Requires-Dist: networkx ==2.5
Requires-Dist: numpy ==1.22.4
Requires-Dist: scipy ==1.9.1
Requires-Dist: torch >=2.0.1
